{
  "cars": [
    {
      "id": "1",
      "make": "Toyota",
      "model": "RAV4",
      "year": 2024,
      "price": 34500,
      "mileage": 0,
      "type": "SUV",
      "transmission": "Automatic",
      "fuelType": "Hybrid",
      "color": "Silver",
      "features": ["Bluetooth", "Backup Camera", "Lane Departure Warning"],
      "images": ["/placeholder.svg?height=300&width=400"],
      "location": "Toronto, ON",
      "dealer": "Toyota Downtown",
      "rating": 4.8,
      "isNew": true,
      "bodyStyle": "SUV",
      "engineSize": "2.5L",
      "horsepower": 219,
      "drivetrain": "AWD"
    },
    {
      "id": "2",
      "make": "Honda",
      "model": "Civic",
      "year": 2023,
      "price": 27500,
      "mileage": 5000,
      "type": "Sedan",
      "transmission": "Automatic",
      "fuelType": "Gasoline",
      "color": "Blue",
      "features": ["Apple CarPlay", "Sunroof", "Adaptive Cruise Control"],
      "images": ["/placeholder.svg?height=300&width=400"],
      "location": "Vancouver, BC",
      "dealer": "Honda West",
      "rating": 4.6,
      "isNew": false,
      "bodyStyle": "Sedan",
      "engineSize": "2.0L",
      "horsepower": 158,
      "drivetrain": "FWD"
    },
    {
      "id": "3",
      "make": "Ford",
      "model": "F-150",
      "year": 2024,
      "price": 52000,
      "mileage": 0,
      "type": "Truck",
      "transmission": "Automatic",
      "fuelType": "Gasoline",
      "color": "Red",
      "features": ["4x4", "Towing Package", "Blind Spot Monitoring"],
      "images": ["/placeholder.svg?height=300&width=400"],
      "location": "Calgary, AB",
      "dealer": "Ford Country",
      "rating": 4.7,
      "isNew": true,
      "bodyStyle": "Pickup",
      "engineSize": "3.5L",
      "horsepower": 400,
      "drivetrain": "4WD"
    },
    {
      "id": "4",
      "make": "Tesla",
      "model": "Model 3",
      "year": 2024,
      "price": 49999,
      "mileage": 0,
      "type": "Sedan",
      "transmission": "Automatic",
      "fuelType": "Electric",
      "color": "White",
      "features": ["Autopilot", "Wireless Charging", "Heated Seats"],
      "images": ["/placeholder.svg?height=300&width=400"],
      "location": "Montreal, QC",
      "dealer": "Tesla Montreal",
      "rating": 4.9,
      "isNew": true,
      "bodyStyle": "Sedan",
      "engineSize": "Electric",
      "horsepower": 283,
      "drivetrain": "RWD"
    },
    {
      "id": "5",
      "make": "BMW",
      "model": "X5",
      "year": 2023,
      "price": 67000,
      "mileage": 12000,
      "type": "SUV",
      "transmission": "Automatic",
      "fuelType": "Gasoline",
      "color": "Black",
      "features": ["Panoramic Sunroof", "Leather Seats", "Harman Kardon Sound System"],
      "images": ["/placeholder.svg?height=300&width=400"],
      "location": "Ottawa, ON",
      "dealer": "BMW Ottawa",
      "rating": 4.8,
      "isNew": false,
      "bodyStyle": "SUV",
      "engineSize": "3.0L",
      "horsepower": 335,
      "drivetrain": "AWD"
    }
  ],
  "makes": [
    "Toyota",
    "Honda",
    "Ford",
    "Chevrolet",
    "BMW",
    "Mercedes-Benz",
    "Audi",
    "Lexus",
    "Porsche",
    "Tesla",
    "Hyundai",
    "Kia"
  ],
  "types": ["SUV", "Sedan", "Truck", "Coupe", "Convertible", "Van", "Wagon", "Hatchback"],
  "bodyStyles": ["SUV", "Sedan", "Pickup", "Coupe", "Convertible", "Van", "Wagon", "Hatchback"],
  "colors": ["Black", "White", "Silver", "Gray", "Red", "Blue", "Green", "Brown", "Gold"],
  "transmissions": ["Automatic", "Manual", "CVT"],
  "fuelTypes": ["Gasoline", "Diesel", "Hybrid", "Electric", "Plug-in Hybrid"],
  "drivetrains": ["FWD", "RWD", "AWD", "4WD"]
}

